gslr/__init__.py
gslr/__main__.py
gslr/gslr.py
gslr-0.0.1.dist-info/DESCRIPTION.rst
gslr-0.0.1.dist-info/METADATA
gslr-0.0.1.dist-info/RECORD
gslr-0.0.1.dist-info/WHEEL
gslr-0.0.1.dist-info/metadata.json
gslr-0.0.1.dist-info/top_level.txt
