Metadata-Version: 2.0
Name: gslr
Version: 0.0.1
Summary: UNKNOWN
Home-page: https://github.com/fraenkel-lab/GSLR
Author: zfrenchee ludwigschmidt
Author-email: alex@lenail.org
License: MIT
Platform: UNKNOWN
Classifier: Programming Language :: Python :: 2.7
Classifier: Programming Language :: Python :: 3.6
Requires-Dist: numpy
Requires-Dist: numba
Requires-Dist: pcst-fast
